{
    "Author": "MorCherlf",
    "Name": "DutyPusher",
    "RepoUrl": "https://github.com/MorCherlf/FFXIVDutyPusher",
    "IconUrl": "https://raw.githubusercontent.com/MorCherlf/FFXIVDutyPusher/master/Resources/img/icon.png",
    "Punchline": "Push notify to your device when your duty is ready",
    "Description": "You can use this plugin to push notify to your device when your duty is ready",
    "ApplicableVersion": "any",
    "DalamudApiLevel": 12,
    "Tags": [
        "utility",
        "Notification"
    ]
}
